pycosat.pyd
test_pycosat.py
pycosat-0.6.1.dist-info/DESCRIPTION.rst
pycosat-0.6.1.dist-info/METADATA
pycosat-0.6.1.dist-info/metadata.json
pycosat-0.6.1.dist-info/RECORD
pycosat-0.6.1.dist-info/top_level.txt
pycosat-0.6.1.dist-info/WHEEL
